handit/__init__.py
handit/tracker.py
handit_sdk-1.16.0.dist-info/METADATA
handit_sdk-1.16.0.dist-info/WHEEL
handit_sdk-1.16.0.dist-info/top_level.txt
handit_sdk-1.16.0.dist-info/RECORD
