Metadata-Version: 2.4
Name: handit-sdk
Version: 1.16.0
Summary: A Python SDK for tracking Model requests and responses.
Home-page: https://github.com/Handit-AI/handit-sdk
Author: Cristhian Camilo Gomez Neira
Author-email: cristhian@handit.ai
Classifier: Programming Language :: Python :: 3
Classifier: License :: OSI Approved :: MIT License
Classifier: Operating System :: OS Independent
Requires-Python: >=3.6
Requires-Dist: requests>=2.31.0
Requires-Dist: jsonpickle>=3.0.2
Requires-Dist: aiohttp>=3.9.1
Dynamic: author
Dynamic: author-email
Dynamic: classifier
Dynamic: description
Dynamic: description-content-type
Dynamic: home-page
Dynamic: requires-dist
Dynamic: requires-python
Dynamic: summary
